crequests
