Metadata-Version: 2.1
Name: crequests
Version: 0.2.1
Summary: A lightweight cache wrapper for requests
Home-page: https://github.com/x821938/crequests
Author: Alex Skov Jensen
Author-email: pydev@offline.dk
License: MIT
Project-URL: Documentation, https://github.com/x821938/crequests
Project-URL: Source, https://github.com/x821938/crequests
Platform: UNKNOWN
Classifier: Programming Language :: Python :: 3
Classifier: Development Status :: 4 - Beta
Classifier: License :: OSI Approved :: MIT License
Classifier: Operating System :: OS Independent
